dynoclick/__init__.py
dynoclick-0.1.1.dist-info/DESCRIPTION.rst
dynoclick-0.1.1.dist-info/METADATA
dynoclick-0.1.1.dist-info/metadata.json
dynoclick-0.1.1.dist-info/RECORD
dynoclick-0.1.1.dist-info/top_level.txt
dynoclick-0.1.1.dist-info/WHEEL
