Metadata-Version: 2.0
Name: dynoclick
Version: 0.1.1
Summary: UNKNOWN
Home-page: https://github.com/a-sk/dynoclick
Author: Alexandr Skurikhin
Author-email: a@skurih.in
License: Copyright (c) 2015 Alexandr Skurikhin
Requires-Dist: click (==4.0)
